{"cameraMode":{"drawMode":0,"name":"Shaded","section":"Shading Mode"},"sceneLighting":true,"audioPlay":false,"sceneViewState":{"m_AlwaysRefresh":false,"showFog":true,"showSkybox":true,"showFlares":true,"showImageEffects":true,"showParticleSystems":true,"showVisualEffectGraphs":true,"m_FxEnabled":true},"in2DMode":false,"pivot":{"x":1.4613559246063233,"y":6.292973041534424,"z":-3.4500465393066408},"rotation":{"x":0.30143606662750246,"y":0.20885434746742249,"z":-0.06784114241600037,"w":0.927874743938446},"size":1.0489262342453004,"orthographic":false}